1 DEF square
2 PUSH_LOCAL param
3 PUSH_LOCAL resultado
4 LOAD_FAST param
5 LOAD_FAST param
6 BINARY_MULTIPLY
7 STORE_FAST resultado
8 LOAD_FAST resultado
9 RETURN_VALUE
10 DEF imprimir
11 PUSH_LOCAL param
12 PUSH_LOCAL num
13 LOAD_CONST 2
14 LOAD_CONST 2
15 BINARY_MULTIPLY
16 LOAD_FAST param
17 BINARY_ADD
18 STORE_FAST num
19 LOAD_FAST num
20 LOAD_GLOBAL square
21 CALL_FUNCTION 1
22 LOAD_FAST num
23 BINARY_SUBSTRACT
24 LOAD_GLOBAL print
25 CALL_FUNCTION 1
26 RETURN
27 DEF Main
28 LOAD_CONST 2
29 LOAD_GLOBAL imprimir
30 CALL_FUNCTION 1
31 END
